package/example_program.py
package/package_main/__init__.py
package/package_main/main.py
package/tests/__init__.py
package/tests/_test.py
runtimeponyo-0.0.6.dist-info/LICENSE
runtimeponyo-0.0.6.dist-info/METADATA
runtimeponyo-0.0.6.dist-info/WHEEL
runtimeponyo-0.0.6.dist-info/top_level.txt
runtimeponyo-0.0.6.dist-info/RECORD
