Metadata-Version: 2.1
Name: runtimeponyo
Version: 0.0.6
Summary: A pacakge that allows the user to record and print out neatly the runtime of function and also the entire program.
Author: Aaron Stein, Alex Hmitti, Rafael Nadal-Scala, Jhon Kim
License: GNU GENERAL PUBLIC LICENSE
Project-URL: Repository, https://github.com/software-students-fall2023/3-python-package-exercise-team-ponyo-squared/tree/main
Keywords: python,package,runtime,profiling
Classifier: Programming Language :: Python :: 3
Classifier: Intended Audience :: Education
Classifier: License :: OSI Approved :: GNU General Public License v3 (GPLv3)
Classifier: Operating System :: OS Independent
Requires-Python: >=3.7
License-File: LICENSE
Provides-Extra: dev
Requires-Dist: pytest ; extra == 'dev'
